ninjasql/__init__.py
ninjasql/app.py
ninjasql/errors.py
ninjasql/settings.py
ninjasql/db/__init__.py
ninjasql/db/history_table.py
ninjasql/db/sqa_dml_extractor.py
ninjasql/db/sqa_table_loads.py
ninjasql/db/staging_table.py
ninjasql/dep/__init__.py
ninjasql/dep/table_dependency.py
ninjasql/templates/__init__.py
ninjasql-0.0.1.dist-info/METADATA
ninjasql-0.0.1.dist-info/WHEEL
ninjasql-0.0.1.dist-info/top_level.txt
ninjasql-0.0.1.dist-info/RECORD
