Metadata-Version: 2.1
Name: ninjasql
Version: 0.0.1
Summary: Create and extract SQL DDL, DMLs and scd2 blueprints.
Home-page: https://github.com/dondaum/ninjasql
Author: Sebastian Daum
Author-email: sebastian.daum89@gmail.com
License: MIT
Platform: UNKNOWN
Classifier: License :: OSI Approved :: MIT License
Classifier: Operating System :: Microsoft :: Windows
Classifier: Operating System :: MacOS :: MacOS X
Classifier: Operating System :: POSIX :: Linux
Classifier: Programming Language :: Python :: 3.6
Classifier: Programming Language :: Python :: 3.7
Classifier: Programming Language :: Python :: 3.8
Requires-Dist: decorator (==4.4.2)
Requires-Dist: networkx (==2.4)
Requires-Dist: numpy (==1.18.2)
Requires-Dist: pandas (==1.0.3)
Requires-Dist: python-dateutil (==2.8.1)
Requires-Dist: pytz (==2019.3)
Requires-Dist: six (==1.14.0)
Requires-Dist: sqlalchemy (==1.3.15)
